{
    "settings": {
        "refreshTime": 300,
        "requestTimestamp": "1663248808"
    },
    "displayScreens": [
        {
            "slug": "lnbits_balance",
            "group": "lnbits",
            "text": [
                {
                    "value": "Wallet Balance",
                    "size": 40,
                    "x": 10,
                    "y": 30
                },
                {
                    "value": "69,420 sats",
                    "size": 20,
                    "x": 10,
                    "y": 90
                }
            ]
        },
        {
            "slug": "mempool_fees",
            "group": "mempool",
            "text": [
                {
                    "value": "Mempool Fees",
                    "size": 20,
                    "x": 10,
                    "y": 30
                },
                {
                    "value": "High priority",
                    "size": 20,
                    "x": 10,
                    "y": 70
                },
                {
                    "value": "50 sats/vbyte",
                    "size": 20,
                    "x": 10,
                    "y": 100
                },
                {
                    "value": "Medium priority",
                    "size": 20,
                    "x": 200,
                    "y": 70
                },
                {
                    "value": "20 sats/vbyte",
                    "size": 20,
                    "x": 200,
                    "y": 100
                },
                {
                    "value": "Low priority",
                    "size": 20,
                    "x": 400,
                    "y": 70
                },
                {
                    "value": "2 sats/vbyte",
                    "size": 20,
                    "x": 400,
                    "y": 100
                }
            ]
        },
        {
            "slug": "current_block_height",
            "group": "mining",
            "text": [
                {
                    "value": "Current block height",
                    "size": 20,
                    "x": 10,
                    "y": 30
                },
                {
                    "value": "420,420",
                    "size": 40,
                    "x": 10,
                    "y": 70
                }
            ]
        },
        {
            "slug": "next_difficulty_adjustment_time",
            "group": "mining",
            "text": [
                {
                    "value": "Estimated time of next difficulty adjustment",
                    "size": 40,
                    "x": 10,
                    "y": 30
                },
                {
                    "value": "27 September 2022 11:07am",
                    "size": 20,
                    "x": 10,
                    "y": 90
                }
            ]
        }
    ]
}
